Workbook

Sheet Summary
A1: Servex - Technical / Security / Architecture Audit
A2: Scope: SQL package and documentation only. Servex frontend, auth code and tests were NOT INSPECTED. Nothing was executed against any database. Not a score or ranking.
A4: Severity | B4: Total | C4: Confirmed | D4: Conditional
A5: P0 | B5: =COUNTIF(Findings!$B$2:$B$20,A5) -> 0 | C5: =COUNTIFS(Findings!$B$2:$B$20,A5,Findings!$C$2:$C$20,"Confirmed") -> 0 | D5: =COUNTIFS(Findings!$B$2:$B$20,A5,Findings!$C$2:$C$20,"Conditional") -> 0
A6: P1 | B6: =COUNTIF(Findings!$B$2:$B$20,A6) -> 1 | C6: =COUNTIFS(Findings!$B$2:$B$20,A6,Findings!$C$2:$C$20,"Confirmed") -> 0 | D6: =COUNTIFS(Findings!$B$2:$B$20,A6,Findings!$C$2:$C$20,"Conditional") -> 1
A7: P2 | B7: =COUNTIF(Findings!$B$2:$B$20,A7) -> 3 | C7: =COUNTIFS(Findings!$B$2:$B$20,A7,Findings!$C$2:$C$20,"Confirmed") -> 3 | D7: =COUNTIFS(Findings!$B$2:$B$20,A7,Findings!$C$2:$C$20,"Conditional") -> 0
A8: P3 | B8: =COUNTIF(Findings!$B$2:$B$20,A8) -> 11 | C8: =COUNTIFS(Findings!$B$2:$B$20,A8,Findings!$C$2:$C$20,"Confirmed") -> 10 | D8: =COUNTIFS(Findings!$B$2:$B$20,A8,Findings!$C$2:$C$20,"Conditional") -> 1
A9: INFO | B9: =COUNTIF(Findings!$B$2:$B$20,A9) -> 4 | C9: =COUNTIFS(Findings!$B$2:$B$20,A9,Findings!$C$2:$C$20,"Confirmed") -> 3 | D9: =COUNTIFS(Findings!$B$2:$B$20,A9,Findings!$C$2:$C$20,"Conditional") -> 1
A10: Total | B10: =SUM(B5:B9) -> 19 | C10: =SUM(C5:C9) -> 16 | D10: =SUM(D5:D9) -> 3
A12: Verification checklist
A13: Open | B13: =COUNTIF('Verification Checklist'!$C$2:$C$19,A13) -> 18
A14: In progress | B14: =COUNTIF('Verification Checklist'!$C$2:$C$19,A14) -> 0
A15: Done | B15: =COUNTIF('Verification Checklist'!$C$2:$C$19,A15) -> 0
A16: Blocked | B16: =COUNTIF('Verification Checklist'!$C$2:$C$19,A16) -> 0
A17: Total checks | B17: =SUM(B13:B16) -> 18
A19: Tabs: Findings | State Machine | RLS Audit | Privacy | Marketplace Risks | Testing | Verification Checklist | Technical Fix Order
A20: Evidence line numbers refer to the SQL package in the audit workspace (backend/migrations), which may differ from the repo's claude22 SQL (verify).
A21: Edit the Status column on the Verification Checklist tab; counts above update automatically.

Sheet Sheet

Sheet Findings
A1: ID | B1: Severity | C1: Type | D1: Component | E1: Evidence (file:line, my SQL copy) | F1: Why it matters | G1: Confidence | H1: Verify in real repo?
A2: S-01 | B2: P2 | C2: Confirmed | D2: RLS / privacy | E2: profiles_select 0005:81-82 allows provider_visible(id); table-wide SELECT grant | F2: Any signed-in user can read the full profile row (email; phone once populated) of any approved provider | G2: High | H2: YES
A3: S-02 | B3: P2 | C3: Confirmed | D3: RLS / privacy | E3: pp_select 0005:96; base_lat/base_lng 0002:80 | F3: All signed-in users can read provider base coordinates (home/base location exposed) | G3: High | H3: YES
A4: S-03 | B4: P2 | C4: Confirmed | D4: Identity link (KI-016) | E4: 0005:84 forces phone is null on client insert; no code reads auth.users except the FK at 0002:14 | F4: Verified phone is never copied into profiles.phone; only link to verified identity is the id FK | G4: High | H4: YES
A5: S-04 | B5: P3 | C5: Confirmed | D5: Duplicate requests | E5: Guard only in RPC (0004:97); unique indexes 0003:201,276,277,385 cover quotes/payments/disputes, not open jobs | F5: Concurrent create_job calls could both pass the duplicate check and the open-request cap | G5: Medium (by reading) | H5: YES
A6: S-05 | B6: P3 | C6: Confirmed | D6: Locking | E6: approve/send/reject_quote lock quote then job (0004:201->203, 225->227, 252->254); create_quote locks job first (0004:167) | F6: Inconsistent lock order; deadlock possible under concurrency | G6: Medium | H6: YES
A7: S-06 | B7: P3 | C7: Confirmed | D7: Input bounds | E7: cancellation_reason 0003:22; history note 0003:41; p_note/p_reason (0004:110,127,248,370) uncapped | F7: Authenticated users can store arbitrarily large text | G7: High | H7: YES
A8: S-07 | B8: P3 | C8: Confirmed | D8: Inspection photos | E8: ip_insert 0005:142 checks inspection ownership only; storage_path unconstrained | F8: Metadata can point to any path string; reads still gated by (unexecuted) Storage RLS | G8: Medium | H8: YES
A9: S-08 | B9: P3 | C9: Confirmed | D9: Reports | E9: disputes_insert_report 0005:170 | F9: Any user can file unlimited reports against any user; no dedupe or rate limit | G9: High | H9: YES
A10: S-09 | B10: P3 | C10: Confirmed | D10: Payments visibility | E10: payments_select 0005:156, table-wide SELECT | F10: Customers see platform_commission and provider_earnings; sensitive given undecided revenue model | G10: Medium | H10: YES
A11: S-10 | B11: P3 | C11: Confirmed | D11: Account deletion | E11: profiles.id ON DELETE CASCADE from auth.users (0002:14) vs 14 ON DELETE RESTRICT FKs (0003) | F11: Deleting an auth user with history fails; no erasure/anonymisation strategy beyond an admin status flag | G11: Medium | H11: YES
A12: S-11 | B12: P3 | C12: Confirmed | D12: Prototype row | E12: ('AWAITING_PAYMENT','PAID','customer') 0003:68 | F12: Customer-actor payment transition exists for demo only; remove when payment_mode = gateway | G12: High | H12: YES
... A20: C-03 | B20: INFO | C20: Conditional | D20: Stale documentation | E20: Older docs say Jordan/Arabic-first | F20: Must not be treated as proof of current implementation | G20: n/a | H20: YES

Sheet State Machine
A1: Current State | B1: Action | C1: Actor | D1: Next State | E1: Evidence | F1: Risk
A2: REQUESTED | B2: Accept (transition_job) | C2: provider | D2: ACCEPTED | E2: 0003:54+ | F2: Requires approved provider (trigger)
A3: REQUESTED | B3: Decline | C3: provider | D3: DECLINED | E3: matrix | F3: None
A4: REQUESTED | B4: Cancel (cancel_job) | C4: customer | D4: CANCELLED | E4: matrix | F4: None
A5: REQUESTED | B5: Expire (expire_stale_jobs) | C5: system | D5: EXPIRED | E5: matrix | F5: Cron not implemented
A6: ACCEPTED | B6: En route | C6: provider | D6: EN_ROUTE | E6: matrix | F6: None
A7: ACCEPTED / EN_ROUTE / ARRIVED / INSPECTION | B7: Cancel | C7: customer or provider | D7: CANCELLED | E7: matrix | F7: No cancellation fees (NOT IMPLEMENTED)
A8: EN_ROUTE | B8: Arrive | C8: provider | D8: ARRIVED | E8: matrix | F8: No location proof
A9: ARRIVED | B9: Start inspection | C9: provider | D9: INSPECTION | E9: matrix | F9: None
A10: INSPECTION | B10: Send quote (send_quote) | C10: provider | D10: QUOTE_SENT | E10: matrix + trigger prerequisites | F10: None
A11: QUOTE_SENT | B11: Approve (approve_quote) | C11: customer | D11: AWAITING_PAYMENT | E11: matrix | F11: Idempotent
A12: QUOTE_SENT | B12: Cancel | C12: customer or provider | D12: CANCELLED | E12: matrix | F12: None
... A22: DECLINED / CANCELLED / EXPIRED | B22: (none) | C22: none | D22: none | E22: static checker: no outgoing edges | F22: Terminal

Sheet RLS Audit
A1: Table | B1: SELECT | C1: INSERT | D1: UPDATE | E1: DELETE
A2: profiles | B2: Self; admin; job counterpart; approved providers (S-01) | C2: Self, role limited, phone NULL | D2: Own cols (name, avatar, email, language) | E2: None
A3: customer_profiles | B3: Self / admin | C3: Self (customer) | D3: Self | E3: None
A4: provider_profiles | B4: Approved / self / admin (S-02) | C4: Self, pending, zeroed | D4: Own non-protected cols | E4: None
A5: provider_* child tables | B5: Visible provider / self / admin | C5: Self | D5: Self | E5: Self
A6: categories, services | B6: Active; admin all | C6: Admin | D6: Admin | E6: None
A7: jobs | B7: Parties / admin | C7: None (RPC) | D7: None (RPC) | E7: None
A8: quotes, quote_items | B8: Provider own; customer non-draft | C8: None (RPC) | D8: None (RPC) | E8: None
A9: payments, invoices, payment_events | B9: Parties / admin; events admin only | C9: None | D9: None | E9: None
A10: reviews | B10: Author / subject / admin; public if approved provider | C10: None (RPC) | D10: None | E10: None
A11: disputes | B11: Parties / opener / admin | C11: Reports only (S-08) | D11: None | E11: None
A12: notifications | B12: Recipient | C12: None | D12: read_at only | E12: None
A13: audit_logs, app_settings | B13: Admin / invisible | C13: None | D13: None | E13: None

Sheet Privacy
A1: Data | B1: Who can access / what | C1: Why it matters | D1: Verify in real repo?
A2: Phone | B2: Counterparties and anyone viewing an approved provider; currently NULL (S-03) | C2: Contact details before a job | D2: YES
A3: Email | B3: Same exposure as phone (S-01) | C3: Unverified, client-editable | D3: YES
A4: Provider coordinates | B4: All authenticated users (S-02) | C4: Provider home/base location | D4: YES
A5: Customer exact job location | B5: Two job parties and admin | C5: Expected | D5: no
A6: Customer default address | B6: Self and admin only | C6: OK | D6: no
A7: Payment data | B7: No card data exists; payment rows visible to parties; commission columns visible (S-09) | C7: Revenue model undecided | D7: YES
A8: Identity documents | B8: NOT IMPLEMENTED | C8: Verification evidence has no storage model | D8: n/a
A9: Inspection photos | B9: Parties and admin (Storage policy, unexecuted) | C9: Private bucket | D9: YES
A10: Portfolio images | B10: Bucket is public (0006:6) | C10: By design | D10: YES
A11: Quotes, reviews, history | B11: Per RLS | C11: OK | D11: YES

Sheet Marketplace Risks
A1: Group | B1: Area | C1: Status
A2: Provider | B2: Profile | C2: Implemented (SQL draft)
A3: Provider | B3: Categories / specialties | C3: Implemented (SQL draft)
A4: Provider | B4: Service area | C4: Partial: radius filter; neighbourhoods stored but not used for filtering
A5: Provider | B5: Availability | C5: Partial: weekly windows only, no exceptions
A6: Provider | B6: Verification | C6: Partial: status + admin RPC; no evidence documents
A7: Provider | B7: Ratings | C7: Implemented (SQL draft)
A8: Provider | B8: Portfolio | C8: Partial: table + bucket
A9: Customer | B9: Request / provider selection | C9: Implemented (SQL draft)
A10: Customer | B10: Location | C10: Partial: raw lat/lng, not validated against city
A11: Customer | B11: Quote / completion / review | C11: Implemented (SQL draft)
A12: Customer | B12: Payment | C12: Simulated
... A21: Frontend aspects | B21: All | C21: Unknown / not inspectable

Sheet Testing
A1: Category | B1: Exists | C1: Executed | D1: Passed | E1: Real Supabase
A2: Static structural checker (static_check.py) | B2: EXISTS | C2: YES | D2: YES (structure only) | E2: n/a
A3: Seed generator assertions | B3: EXISTS | C3: YES | D3: YES | E3: n/a
A4: pgTAP DB/RLS tests (001_behavior.test.sql) | B4: EXISTS (18 assertions) | C4: NO | D4: n/a | E4: NO; S-13 defect likely
A5: Claimed PostgreSQL 16 behavioural tests | B5: UNKNOWN | C5: UNKNOWN | D5: UNKNOWN | E5: NO (substitute is not Supabase)
A6: Auth / unit / integration / E2E / browser / responsive | B6: UNKNOWN | C6: UNKNOWN | D6: UNKNOWN | E6: UNKNOWN
A7: Role-boundary / RLS tests | B7: Partial (few pgTAP assertions) | C7: NO | D7: n/a | E7: NO

Sheet Verification Checklist
A1: # | B1: Check | C1: Status | D1: Notes
A2: 1 | B2: Obtain full ZIP; inspect package.json, src/, routes, hooks, services | C2: Open
A3: 2 | B3: Diff repo claude22 SQL against my copy; record differences | C3: Open
A4: 3 | B4: Re-test S-01 to S-12 against the repo's SQL | C4: Open
A5: 4 | B5: Confirm market: Israel / English-first; check +972 phone validation, cities, currency, timezone, name_ar, languages | C5: Open
A6: 5 | B6: Verify English/LTR implementation, accessibility, responsive layout | C6: Open
A7: 6 | B7: Inspect auth: login, OTP, registration, role selection, logout, session storage | C7: Open
A8: 7 | B8: Confirm KI-016 in repo and how verified phone is stored | C8: Open
A9: 8 | B9: Inspect Customer, Provider and Admin pages; route guards; role manipulation from client | C9: Open
A10: 9 | B10: Verify admin bootstrap path; no client can self-assign admin | C10: Open
A11: 10 | B11: Inspect Supabase client and env files; ensure no service-role key in client bundle | C11: Open
A12: 11 | B12: Inspect demo-flag isolation (demo OTP, mock data, simulated payment) | C12: Open
A13: 12 | B13: Inspect upload handling and dangerouslySetInnerHTML / XSS surfaces | C13: Open
... A19: 18 | B19: Verify documentation vs code (SESSION_HANDOFF.md, FILE_MAP.md) | C19: Open

Sheet Technical Fix Order
A1: Order | B1: Verify / fix | C1: Findings
A2: 1 | B2: Get the real repo and diff the SQL (everything is conditional until then) | C2: All
A3: 2 | B3: Confirm market and language, then decide C-01 | C3: C-01
A4: 3 | B4: Execute migrations and tests on local Supabase (gate for all SQL findings) | C4: S-13, all SQL
A5: 4 | B5: Phone linking with privacy exposures | C5: S-03, S-01, S-02
A6: 5 | B6: Race and lock order; input bounds, reports, commission visibility | C6: S-04, S-05, S-06, S-07, S-08, S-09
A7: 6 | B7: Deletion strategy, prototype row, seed guard (before any non-dev deployment) | C7: S-10, S-11, S-12
A8: 7 | B8: Fix the test defect when tests are first run | C8: S-13
